data2Image/models.py
data2image_alpha-0.0.1.dist-info/METADATA
data2image_alpha-0.0.1.dist-info/WHEEL
data2image_alpha-0.0.1.dist-info/licenses/LICENSE
data2image_alpha-0.0.1.dist-info/RECORD
