Metadata-Version: 2.1
Name: data2image-alpha
Version: 0.0.1
Summary: Converting tabular data into images
Project-URL: Homepage, https://github.com/oeg-upm/TINTO
Author-email: BorjaRei <borjareinoso@gmail.com>
License:                                  Apache License
License-File: LICENSE
Classifier: License :: OSI Approved :: Apache Software License
Classifier: Operating System :: OS Independent
Classifier: Programming Language :: Python :: 3
Requires-Python: >=3.8
